[
  { "id": "0", "name": "Software de navegación HYDRO PRO / HYPACK" },
  { "id": "1", "name": "SURFER 8" },
  { "id": "2", "name": "Global Mapper 8" },
  { "id": "3", "name": "AutoCad - Civil 3d - ReCap" },
  { "id": "4", "name": "Trimble Business Center" },
  { "id": "5", "name": "PIX 4d" },
  { "id": "6", "name": "Side Scan Sonar TRITONISIS V.5.75" },
  { "id": "7", "name": "DELPHMAP V.2.80" },
  { "id": "8", "name": "Adquisión y procesamiento de subBottom - DELPSEISMIC" },
  { "id": "9", "name": "Medicicon Magnetómetro MAGLOG" },
  { "id": "10","name": "Procesamiento de data del Magnetómetro - MAGMAP 2000"},
  { "id": "11", "name": "GEODVEN V.1.6" },
  {
    "id": "12",
    "name": "Corrientímetro: Software de comunicación y procesamiento"
  }
]
